raku_scraper/__init__.py
raku_scraper/scraper.py
tests/__init__.py
raku_scraper-0.1.1.dist-info/LICENSE
raku_scraper-0.1.1.dist-info/METADATA
raku_scraper-0.1.1.dist-info/WHEEL
raku_scraper-0.1.1.dist-info/top_level.txt
raku_scraper-0.1.1.dist-info/RECORD
