Metadata-Version: 2.1
Name: raku-scraper
Version: 0.1.1
Summary: A simple web scraping and automation tool
Home-page: https://github.com/pyrdnv/raku-scraper
Author: Petar Yordanov
Author-email: petaryrdnv@gmail.com
Classifier: Programming Language :: Python :: 3
Classifier: License :: OSI Approved :: GNU General Public License v3 (GPLv3)
Classifier: Operating System :: OS Independent
Requires-Python: >=3.6
License-File: LICENSE
Requires-Dist: selenium
